ai_sec/__init__.py
ai_sec/ai_assist/__init__.py
ai_sec/ai_assist/issue_handler.py
ai_sec/config.py
ai_sec/lint_factory.py
ai_sec/linter_runner.py
ai_sec/linters/__init__.py
ai_sec/linters/base_linter.py
ai_sec/linters/checkov.py
ai_sec/linters/tflint.py
ai_sec/linters/tfsec.py
ai_sec/models/__init__.py
ai_sec/models/checkov_model.py
ai_sec/models/tflint_model.py
ai_sec/models/tfsec_model.py
ai_sec/processor/__init__.py
ai_sec/processor/ai_processor.py
ai_sec/processor/checkov_processor.py
ai_sec/processor/lint_processor.py
ai_sec/processor/tflint_processor.py
ai_sec/processor/tfsec_processor.py
ai_sec/reporting/__init__.py
ai_sec/reporting/api.py
ai_sec/reporting/app_layout.py
ai_sec/reporting/assets/custom.css
ai_sec/reporting/assets/custom.js
ai_sec/reporting/assets/home-solid.svg
ai_sec/reporting/assets/home.svg
ai_sec/reporting/assets/logo.webp
ai_sec/reporting/base.py
ai_sec/reporting/bugfixes.txt
ai_sec/reporting/callbacks.py
ai_sec/reporting/components.py
ai_sec/reporting/dashboard.py
ai_sec/reporting/data_loader.py
ai_sec/resources/__init__.py
ai_sec/resources/config.yaml
ai_sec/resources/custom_styles.css
ai_sec/resources/report.js
ai_sec/utils/__init__.py
ai_sec/utils/config_utils.py
ai_sec/utils/file_utils.py
ai_sec/utils/infra_utils.py
ai_sec/utils/linter_checker.py
ai_sec/utils/report_generator.py
ai_sec/utils/report_summary.py
ai_sec/utils/report_to_html.py
ai_sec-0.0.9.dist-info/METADATA
ai_sec-0.0.9.dist-info/WHEEL
ai_sec-0.0.9.dist-info/entry_points.txt
ai_sec-0.0.9.dist-info/RECORD
