Metadata-Version: 2.3
Name: ai_sec
Version: 0.0.9
Summary: Linting, security scanning, and reporting on infrastructure code and Kubernetes config
License: MIT
Author: Darren Rabbitt
Maintainer: Darren Rabbitt
Maintainer-email: dev@darrenrabbitt.com
Requires-Python: >=3.10,<4.0
Classifier: License :: OSI Approved :: MIT License
Classifier: Programming Language :: Python :: 3
Classifier: Programming Language :: Python :: 3.10
Classifier: Programming Language :: Python :: 3.11
Classifier: Programming Language :: Python :: 3.12
Classifier: Programming Language :: Python :: 3.13
Requires-Dist: Jinja2 (>=3.1.4,<4.0.0)
Requires-Dist: PyYAML (>=6.0.2,<7.0.0)
Requires-Dist: aiofiles (>=24.1.0,<25.0.0)
Requires-Dist: checkov (>=3.2.267,<4.0.0)
Requires-Dist: click (>=8.1.7,<9.0.0)
Requires-Dist: dash (>=2.18.0,<3.0.0)
Requires-Dist: dash-bootstrap-components (>=1.6.0,<2.0.0)
Requires-Dist: ijson (>=3.3.0,<4.0.0)
Requires-Dist: pandas (>=2.2.2,<3.0.0)
Requires-Dist: pytest-flask (>=1.3.0,<2.0.0)
